jeffutils/__init__.py
jeffutils/analytics.py
jeffutils/utils.py
jeffutils-0.9.8.dist-info/LICENSE.txt
jeffutils-0.9.8.dist-info/METADATA
jeffutils-0.9.8.dist-info/WHEEL
jeffutils-0.9.8.dist-info/top_level.txt
jeffutils-0.9.8.dist-info/RECORD
